curation_projects/__init__.py
curation_projects/abhidhaanamanjarii.py
curation_projects/bhagavad-go-maNDala.py
curation_projects/pAli.py
curation_projects/shabda_kasustubha.py
curation_projects/conversion/__init__.py
curation_projects/conversion/alar.py
curation_projects/conversion/autocomplete.py
curation_projects/conversion/babylon/__init__.py
curation_projects/conversion/babylon/aakhyaatachandrikaa.py
curation_projects/conversion/babylon/apte_sa.py
curation_projects/conversion/babylon/datuk2babylon.py
curation_projects/conversion/babylon/hi_shabdasAgar.py
curation_projects/conversion/babylon/jnu_tinanta.py
curation_projects/conversion/babylon/kalpadruma.py
curation_projects/conversion/babylon/kalpadruma_simple_dict.py
curation_projects/conversion/babylon/olam2babylon.py
curation_projects/conversion/babylon/tulasI_kosha.py
curation_projects/conversion/babylon/vAchaspatyam.py
curation_projects/conversion/babylon/vedic_rituals.py
dict_curation/__init__.py
dict_curation/babylon.py
dict_curation/slob/__init__.py
dict_curation-0.0.3.dist-info/LICENSE.txt
dict_curation-0.0.3.dist-info/METADATA
dict_curation-0.0.3.dist-info/WHEEL
dict_curation-0.0.3.dist-info/top_level.txt
dict_curation-0.0.3.dist-info/RECORD
